{
  "spacing": {
    "scale": {
      "0": { "value": "0px" },
      "1": { "value": "4px" },
      "2": { "value": "8px" },
      "3": { "value": "12px" },
      "4": { "value": "16px" },
      "5": { "value": "20px" },
      "6": { "value": "24px" },
      "7": { "value": "28px" },
      "8": { "value": "32px" },
      "9": { "value": "36px" },
      "10": { "value": "40px" },
      "11": { "value": "56px" },
      "12": { "value": "60px" }
    },
    "container": {
      "max-width": { "value": "1440px" },
      "content-width": { "value": "1200px" },
      "padding": {
        "desktop": { "value": "32px" },
        "tablet": { "value": "24px" },
        "mobile": { "value": "16px" }
      }
    },
    "grid": {
      "columns": { "value": "12" },
      "gutter": { "value": "16px" },
      "card-gap": { "value": "24px" }
    },
    "touch-target": {
      "minimum": { "value": "44px" },
      "comfortable": { "value": "48px" }
    }
  }
}
